{
  "/__docusaurus/debug-5ff": {
    "__comp": "__comp---theme-debug-config-23-a-2ff",
    "__context": {
      "plugin": "plugin---docusaurus-debugb-38-ad3"
    }
  },
  "/__docusaurus/debug/config-5ba": {
    "__comp": "__comp---theme-debug-config-23-a-2ff",
    "__context": {
      "plugin": "plugin---docusaurus-debugb-38-ad3"
    }
  },
  "/__docusaurus/debug/content-a2b": {
    "__comp": "__comp---theme-debug-contentba-8-ce7",
    "__context": {
      "plugin": "plugin---docusaurus-debugb-38-ad3"
    },
    "__props": "__props---docusaurus-debug-content-3-c-0-be2"
  },
  "/__docusaurus/debug/globalData-c3c": {
    "__comp": "__comp---theme-debug-global-dataede-0fa",
    "__context": {
      "plugin": "plugin---docusaurus-debugb-38-ad3"
    }
  },
  "/__docusaurus/debug/metadata-156": {
    "__comp": "__comp---theme-debug-site-metadata-68-e-3d4",
    "__context": {
      "plugin": "plugin---docusaurus-debugb-38-ad3"
    }
  },
  "/__docusaurus/debug/registry-88c": {
    "__comp": "__comp---theme-debug-registry-679-501",
    "__context": {
      "plugin": "plugin---docusaurus-debugb-38-ad3"
    }
  },
  "/__docusaurus/debug/routes-000": {
    "__comp": "__comp---theme-debug-routes-946-699",
    "__context": {
      "plugin": "plugin---docusaurus-debugb-38-ad3"
    }
  },
  "/about-ca4": {
    "__comp": "__comp---site-src-pages-about-tsx-618-aa9",
    "__context": {
      "plugin": "plugin---abouta-74-d48"
    },
    "config": "config---artwork-0015-e-9-8ae"
  },
  "/artwork-001-985": {
    "__comp": "__comp---site-src-pages-artwork-001-tsx-6-b-5-2a6",
    "__context": {
      "plugin": "plugin---abouta-74-d48"
    },
    "config": "config---artwork-0015-e-9-8ae"
  },
  "/blog-308": {
    "__comp": "__comp---theme-blog-list-pagea-6-a-7ba",
    "__context": {
      "plugin": "plugin---blog-369-22e"
    },
    "sidebar": "sidebar---blog-814-8ac",
    "items": [
      {
        "content": "content---blog-7-c-0-0a1"
      }
    ],
    "__props": "__props---blogc-15-573"
  },
  "/blog/archive-182": {
    "__comp": "__comp---theme-blog-archive-page-9-e-4-1d8",
    "__context": {
      "plugin": "plugin---blog-369-22e"
    },
    "__props": "__props---blog-archivef-81-229"
  },
  "/blog/authors-0b7": {
    "__comp": "__comp---theme-blog-pages-blog-authors-list-page-621-70c",
    "__context": {
      "data": {
        "blogMetadata": "blogMetadata---blog-authorsace-e7d"
      },
      "plugin": "plugin---blog-369-22e"
    },
    "sidebar": "sidebar---blog-814-8ac",
    "__props": "__props---blog-authorsef-8-44f"
  },
  "/blog/authors/xinxian-3cc": {
    "__comp": "__comp---theme-blog-pages-blog-authors-posts-page-33-f-bd5",
    "__context": {
      "data": {
        "blogMetadata": "blogMetadata---blog-authorsace-e7d"
      },
      "plugin": "plugin---blog-369-22e"
    },
    "items": [
      {
        "content": "content---blog-7-c-0-0a1"
      }
    ],
    "sidebar": "sidebar---blog-814-8ac",
    "__props": "__props---blog-authors-xinxianc-35-aff"
  },
  "/blog/beginning-43c": {
    "__comp": "__comp---theme-blog-post-pageccc-cab",
    "__context": {
      "data": {
        "blogMetadata": "blogMetadata---blog-authorsace-e7d"
      },
      "plugin": "plugin---blog-369-22e"
    },
    "sidebar": "sidebar---blog-814-8ac",
    "content": "content---blog-beginning-047-824"
  },
  "/blog/tags-287": {
    "__comp": "__comp---theme-blog-tags-list-page-01-a-d0b",
    "__context": {
      "plugin": "plugin---blog-369-22e"
    },
    "sidebar": "sidebar---blog-814-8ac",
    "__props": "__props---blog-tags-3-a-2-fa2"
  },
  "/blog/tags/东方Project-c82": {
    "__comp": "__comp---theme-blog-tags-posts-page-687-b6c",
    "__context": {
      "plugin": "plugin---blog-369-22e"
    },
    "sidebar": "sidebar---blog-814-8ac",
    "items": [
      {
        "content": "content---blog-7-c-0-0a1"
      }
    ],
    "__props": "__props---blog-tags-东方-projecta-8-b-1bd"
  },
  "/blog/tags/创立-ce1": {
    "__comp": "__comp---theme-blog-tags-posts-page-687-b6c",
    "__context": {
      "plugin": "plugin---blog-369-22e"
    },
    "sidebar": "sidebar---blog-814-8ac",
    "items": [
      {
        "content": "content---blog-7-c-0-0a1"
      }
    ],
    "__props": "__props---blog-tags-创立-9-d-3-537"
  },
  "/blog/tags/名画同人-c45": {
    "__comp": "__comp---theme-blog-tags-posts-page-687-b6c",
    "__context": {
      "plugin": "plugin---blog-369-22e"
    },
    "sidebar": "sidebar---blog-814-8ac",
    "items": [
      {
        "content": "content---blog-7-c-0-0a1"
      }
    ],
    "__props": "__props---blog-tags-名画同人-78-a-633"
  },
  "/blog/tags/社团-ddd": {
    "__comp": "__comp---theme-blog-tags-posts-page-687-b6c",
    "__context": {
      "plugin": "plugin---blog-369-22e"
    },
    "sidebar": "sidebar---blog-814-8ac",
    "items": [
      {
        "content": "content---blog-7-c-0-0a1"
      }
    ],
    "__props": "__props---blog-tags-社团-9-c-0-682"
  },
  "/contact-a03": {
    "__comp": "__comp---site-src-pages-contact-tsx-8-b-3-cf6",
    "__context": {
      "plugin": "plugin---abouta-74-d48"
    },
    "config": "config---artwork-0015-e-9-8ae"
  },
  "/friends-fc6": {
    "__comp": "__comp---site-src-pages-friends-tsx-389-9fa",
    "__context": {
      "plugin": "plugin---abouta-74-d48"
    },
    "config": "config---artwork-0015-e-9-8ae"
  },
  "/gallery-5cb": {
    "__comp": "__comp---site-src-pages-gallery-tsxaf-3-bcf",
    "__context": {
      "plugin": "plugin---abouta-74-d48"
    },
    "config": "config---artwork-0015-e-9-8ae"
  },
  "/markdown-page-3d7": {
    "__comp": "__comp---theme-mdx-page-1-f-3-b90",
    "__context": {
      "plugin": "plugin---abouta-74-d48"
    },
    "content": "content---markdown-page-393-028"
  },
  "/qq-group-a46": {
    "__comp": "__comp---site-src-pages-qq-group-tsx-40-e-316",
    "__context": {
      "plugin": "plugin---abouta-74-d48"
    },
    "config": "config---artwork-0015-e-9-8ae"
  },
  "/-e5f": {
    "__comp": "__comp---site-src-pages-index-tsx-1-df-d3e",
    "__context": {
      "plugin": "plugin---abouta-74-d48"
    },
    "config": "config---artwork-0015-e-9-8ae"
  }
}